scine_serenity_wrapper/LICENSE.txt
scine_serenity_wrapper/__init__.py
scine_serenity_wrapper/libutilsos.so
scine_serenity_wrapper/serenity.module.so
scine_serenity_wrapper/Tests/__init__.py
scine_serenity_wrapper/Tests/test_calculators.py
scine_serenity_wrapper/Tests/resources/__init__.py
scine_serenity_wrapper/Tests/resources/etoh-water-charges.pc
scine_serenity_wrapper/Tests/resources/etoh.xyz
scine_serenity_wrapper/Tests/resources/protein-ligand-fragment.xyz
scine_serenity_wrapper/Tests/resources/protein-point-charges.pc
scine_serenity_wrapper/data/basis/3-21G
scine_serenity_wrapper/data/basis/4-31G
scine_serenity_wrapper/data/basis/6-31++GS
scine_serenity_wrapper/data/basis/6-31++GSS
scine_serenity_wrapper/data/basis/6-31+G
scine_serenity_wrapper/data/basis/6-31+GS
scine_serenity_wrapper/data/basis/6-31+GSS
scine_serenity_wrapper/data/basis/6-311+G
scine_serenity_wrapper/data/basis/6-311+GS
scine_serenity_wrapper/data/basis/6-311+GSS
scine_serenity_wrapper/data/basis/6-311G
scine_serenity_wrapper/data/basis/6-311GS
scine_serenity_wrapper/data/basis/6-311GSS
scine_serenity_wrapper/data/basis/6-31G
scine_serenity_wrapper/data/basis/6-31GS
scine_serenity_wrapper/data/basis/6-31GSS
scine_serenity_wrapper/data/basis/ANO-RCC
scine_serenity_wrapper/data/basis/AUG-CC-PV5Z
scine_serenity_wrapper/data/basis/AUG-CC-PV5Z-RI-C
scine_serenity_wrapper/data/basis/AUG-CC-PV6Z
scine_serenity_wrapper/data/basis/AUG-CC-PV6Z-RI-C
scine_serenity_wrapper/data/basis/AUG-CC-PVDZ
scine_serenity_wrapper/data/basis/AUG-CC-PVDZ-RI-C
scine_serenity_wrapper/data/basis/AUG-CC-PVQZ
scine_serenity_wrapper/data/basis/AUG-CC-PVQZ-RI-C
scine_serenity_wrapper/data/basis/AUG-CC-PVTZ
scine_serenity_wrapper/data/basis/AUG-CC-PVTZ-RI-C
scine_serenity_wrapper/data/basis/CC-PV5Z
scine_serenity_wrapper/data/basis/CC-PV5Z-RI-C
scine_serenity_wrapper/data/basis/CC-PV6Z
scine_serenity_wrapper/data/basis/CC-PV6Z-RI-C
scine_serenity_wrapper/data/basis/CC-PVDZ
scine_serenity_wrapper-4.0.0.dist-info/METADATA
scine_serenity_wrapper-4.0.0.dist-info/WHEEL
scine_serenity_wrapper-4.0.0.dist-info/top_level.txt
scine_serenity_wrapper-4.0.0.dist-info/RECORD
